Metadata-Version: 1.0
Name: prod
Version: 0.7
Summary: If they have sum(), why not product()
Home-page: UNKNOWN
Author: UNKNOWN
Author-email: UNKNOWN
License: UNKNOWN
Keywords: product sum
Platform: UNKNOWN
